README.md
setup.py
root_pandas/__init__.py
root_pandas/readwrite.py
root_pandas/utils.py
root_pandas/version.py
root_pandas.egg-info/PKG-INFO
root_pandas.egg-info/SOURCES.txt
root_pandas.egg-info/dependency_links.txt
root_pandas.egg-info/not-zip-safe
root_pandas.egg-info/requires.txt
root_pandas.egg-info/top_level.txt