Metadata-Version: 1.2
Name: root-pandas
Version: 0.6.1
Summary: Read and save pandas DataFrames from and to ROOT files
Home-page: http://github.com/scikit-hep/root_pandas
Author: the root_pandas developers
Maintainer: Chris Burr
Maintainer-email: c.b@cern.ch
License: MIT
Platform: UNKNOWN
